{
  "stats": {
    "tconstruct:binding": {},
    "tconstruct:handle": {
      "durability": 0.5,
      "mining_speed": 0.2,
      "melee_speed": 0.15,
      "melee_damage": 0.1
    },
    "tconstruct:head": {
      "durability": 1500,
      "mining_speed": 6.5,
      "mining_tier": "tinkers_ingenuity:sea_dream",
      "melee_attack": 5.75
    },
    "tconstruct:limb": {
      "durability": 1500,
      "draw_speed": 0.2,
      "velocity": 0.1,
      "accuracy": 0.1
    },
    "tconstruct:grip": {
      "durability": 0.5,
      "accuracy": 0.15,
      "melee_damage": 5.5
    },
    "tconstruct:maille": {},
    "tconstruct:plating_helmet": {
      "armor": 4.0,
      "durability": 1200,
      "knockback_resistance": 0.005,
      "toughness": 1.5
    },
    "tconstruct:plating_chestplate": {
      "armor": 7.0,
      "durability": 1450,
      "knockback_resistance": 0.005,
      "toughness": 1.5
    },
    "tconstruct:plating_leggings": {
      "armor": 5.0,
      "durability": 1350,
      "knockback_resistance": 0.005,
      "toughness": 1.5
    },
    "tconstruct:plating_boots": {
      "armor": 4.0,
      "durability": 1200,
      "knockback_resistance": 0.005,
      "toughness": 1.5
    }
  }
}